simple_backtester/__init__.py
simple_backtester/data.py
simple_backtester/order.py
simple_backtester/strat.py
simple_backtester/types.py
simple_backtester-0.1.1.dist-info/LICENSE
simple_backtester-0.1.1.dist-info/METADATA
simple_backtester-0.1.1.dist-info/WHEEL
simple_backtester-0.1.1.dist-info/RECORD
