Metadata-Version: 2.1
Name: simple-backtester
Version: 0.1.1
Summary: Simple, no frills backtesting
License: MIT
Keywords: backtesting
Author: Shida SB
Author-email: ssbakh07@gmail.com
Requires-Python: >=3.9
Classifier: License :: OSI Approved :: MIT License
Classifier: Programming Language :: Python :: 3
Classifier: Programming Language :: Python :: 3.9
Classifier: Programming Language :: Python :: 3.10
Classifier: Programming Language :: Python :: 3.11
Classifier: Programming Language :: Python :: 3.12
Classifier: Programming Language :: Python :: 3.13
Requires-Dist: numpy (>1.26.0,<2.0.0)
Requires-Dist: pandas
Requires-Dist: setuptools ; python_version < "3.10"
Requires-Dist: tqdm
